ZhihuWendaXiangBaZijiDeShujiSaomiaoChengPdfShenmeyangDeSaomiaoyiBijiaoHeshi/README.md
ZhihuWendaXiangBaZijiDeShujiSaomiaoChengPdfShenmeyangDeSaomiaoyiBijiaoHeshi/__init__.py
ZhihuWendaXiangBaZijiDeShujiSaomiaoChengPdfShenmeyangDeSaomiaoyiBijiaoHeshi/__main__.py
ZhihuWendaXiangBaZijiDeShujiSaomiaoChengPdfShenmeyangDeSaomiaoyiBijiaoHeshi/file.epub
ZhihuWendaXiangBaZijiDeShujiSaomiaoChengPdfShenmeyangDeSaomiaoyiBijiaoHeshi/index.html
ZhihuWendaXiangBaZijiDeShujiSaomiaoChengPdfShenmeyangDeSaomiaoyiBijiaoHeshi/css/__init__.py
ZhihuWendaXiangBaZijiDeShujiSaomiaoChengPdfShenmeyangDeSaomiaoyiBijiaoHeshi/css/annotations.css
ZhihuWendaXiangBaZijiDeShujiSaomiaoChengPdfShenmeyangDeSaomiaoyiBijiaoHeshi/css/main.css
ZhihuWendaXiangBaZijiDeShujiSaomiaoChengPdfShenmeyangDeSaomiaoyiBijiaoHeshi/css/normalize.css
ZhihuWendaXiangBaZijiDeShujiSaomiaoChengPdfShenmeyangDeSaomiaoyiBijiaoHeshi/css/popup.css
ZhihuWendaXiangBaZijiDeShujiSaomiaoChengPdfShenmeyangDeSaomiaoyiBijiaoHeshi/font/__init__.py
ZhihuWendaXiangBaZijiDeShujiSaomiaoChengPdfShenmeyangDeSaomiaoyiBijiaoHeshi/font/fontello.eot
ZhihuWendaXiangBaZijiDeShujiSaomiaoChengPdfShenmeyangDeSaomiaoyiBijiaoHeshi/font/fontello.svg
ZhihuWendaXiangBaZijiDeShujiSaomiaoChengPdfShenmeyangDeSaomiaoyiBijiaoHeshi/font/fontello.ttf
ZhihuWendaXiangBaZijiDeShujiSaomiaoChengPdfShenmeyangDeSaomiaoyiBijiaoHeshi/font/fontello.woff
ZhihuWendaXiangBaZijiDeShujiSaomiaoChengPdfShenmeyangDeSaomiaoyiBijiaoHeshi/img/__init__.py
ZhihuWendaXiangBaZijiDeShujiSaomiaoChengPdfShenmeyangDeSaomiaoyiBijiaoHeshi/img/annotator-glyph-sprite.png
ZhihuWendaXiangBaZijiDeShujiSaomiaoChengPdfShenmeyangDeSaomiaoyiBijiaoHeshi/img/annotator-icon-sprite.png
ZhihuWendaXiangBaZijiDeShujiSaomiaoChengPdfShenmeyangDeSaomiaoyiBijiaoHeshi/img/apple-touch-icon.png
ZhihuWendaXiangBaZijiDeShujiSaomiaoChengPdfShenmeyangDeSaomiaoyiBijiaoHeshi/img/cancelfullscreen.png
ZhihuWendaXiangBaZijiDeShujiSaomiaoChengPdfShenmeyangDeSaomiaoyiBijiaoHeshi/img/close.png
zhihu_wenda_xiang_ba_ziji_de_shuji_saomiao_cheng_pdf_shenmeyang_de_saomiaoyi_bijiao_heshi-2024.3.5.0.dist-info/METADATA
zhihu_wenda_xiang_ba_ziji_de_shuji_saomiao_cheng_pdf_shenmeyang_de_saomiaoyi_bijiao_heshi-2024.3.5.0.dist-info/WHEEL
zhihu_wenda_xiang_ba_ziji_de_shuji_saomiao_cheng_pdf_shenmeyang_de_saomiaoyi_bijiao_heshi-2024.3.5.0.dist-info/entry_points.txt
zhihu_wenda_xiang_ba_ziji_de_shuji_saomiao_cheng_pdf_shenmeyang_de_saomiaoyi_bijiao_heshi-2024.3.5.0.dist-info/top_level.txt
zhihu_wenda_xiang_ba_ziji_de_shuji_saomiao_cheng_pdf_shenmeyang_de_saomiaoyi_bijiao_heshi-2024.3.5.0.dist-info/RECORD
